LICENSE
MANIFEST.in
readme.md
requirements.txt
setup.py
ProxyFinder/__init__.py
ProxyFinder.egg-info/PKG-INFO
ProxyFinder.egg-info/SOURCES.txt
ProxyFinder.egg-info/dependency_links.txt
ProxyFinder.egg-info/requires.txt
ProxyFinder.egg-info/top_level.txt
ProxyFinder/ProxyProviders/__init__.py
ProxyFinder/ProxyProviders/free_proxy_list.py
ProxyFinder/ProxyProviders/sslproxies.py