Metadata-Version: 2.1
Name: ProxyFinder
Version: 2022.7.17.1
Summary: UNKNOWN
Home-page: https://github.com/ulbwazhine/ProxyFinder
Author: Ulbwazhine
Author-email: ulbwa@icloud.com
License: MIT
Platform: UNKNOWN
License-File: LICENSE
